Workbook

Sheet Data
B1: Model Drivers & Historical Inputs
B2: Fare | C2: 220
B3: Inflation | C3: =3% -> 0.03
B4: Fuel Cost Per Gallon | C4: 2.3
B5: Number of Aircraft Leased | C5: =40 -> 40
B10: Column1 | C10: 2022 | D10: 2023 | E10: 2024 | F10: Averages | H10: Avg Rates
B11: Operating Revenues
B12: Passenger | C12: =(2137762)*1000 -> 2137762000 | D12: =(2324387)*1000 -> 2324387000 | E12: =(2217059)*1000 -> 2217059000 | F12: =AVERAGE(Table4[[#This Row],[2022]:[2024]]) -> 2.2264027e+09
B13: Third Party Products | C13: =(100959)*1000 -> 100959000 | D13: =(112579)*1000 -> 112579000 | E13: =(142128)*1000 -> 142128000 | F13: =AVERAGE(Table4[[#This Row],[2022]:[2024]]) -> 1.1855533e+08
B14: Fixed Fee Contracts | C14: =(60937)*1000 -> 60937000 | D14: =(68548)*1000 -> 68548000 | E14: =(80660)*1000 -> 80660000 | F14: =AVERAGE(Table4[[#This Row],[2022]:[2024]]) -> 70048333 | G14: Fixed Fee Growth Rate | H14: =AVERAGE((Table4[[#This Row],[2023]]/Table4[[#This Row],[2022]])-1,(Table4[[#This Row],[2024]]/Table4[[#This Row],[2023]])-1) -> 0.1507966
B15: Resort and Other | C15: =(2171)*1000 -> 2171000 | D15: =(4333)*1000 -> 4333000 | E15: =(72742)*1000 -> 72742000 | F15: =AVERAGE(Table4[[#This Row],[2022]:[2024]]) -> 26415333
B18: Operating Expenses
B19: Salaries and Benefits | C19: =(552413)*1000 -> 552413000 | D19: =(687803)*1000 -> 687803000 | E19: =(819843)*1000 -> 819843000 | F19: =AVERAGE(Table4[[#This Row],[2022]:[2024]]) -> 6.8668633e+08 | G19: Wage Inflation | H19: =AVERAGE((Table4[[#This Row],[2023]]/Table4[[#This Row],[2022]])-1,(Table4[[#This Row],[2024]]/Table4[[#This Row],[2023]])-1) -> 0.21853097
B20: Aircraft Fuel | C20: =(814803)*1000 -> 814803000 | D20: =(695871)*1000 -> 695871000 | E20: =(627755)*1000 -> 627755000 | F20: =AVERAGE(Table4[[#This Row],[2022]:[2024]]) -> 7.1280967e+08
B21: Station Operations | C21: =(255168)*1000 -> 255168000 | D21: =(256560)*1000 -> 256560000 | E21: =(272843)*1000 -> 272843000 | F21: =AVERAGE(Table4[[#This Row],[2022]:[2024]]) -> 2.6152367e+08 | G21: Stations Ops Rate | H21: =AVERAGE((Table4[[#This Row],[2023]]/Table4[[#This Row],[2022]])-1,(Table4[[#This Row],[2024]]/Table4[[#This Row],[2023]])-1) -> 0.034460932
B22: Depreciation and amoritzation | C22: =(197542)*1000 -> 197542000 | D22: =(223130)*1000 -> 223130000 | E22: =(258251)*1000 -> 258251000 | F22: =AVERAGE(Table4[[#This Row],[2022]:[2024]]) -> 2.2630767e+08 | G22: Depreciation Rate | H22: =AVERAGE((Table4[[#This Row],[2023]]/Table4[[#This Row],[2022]])-1,(Table4[[#This Row],[2024]]/Table4[[#This Row],[2023]])-1) -> 0.14346673
B23: Maintenance and Repairs | C23: =(117814)*1000 -> 117814000 | D23: =(123802)*1000 -> 123802000 | E23: =(125430)*1000 -> 125430000 | F23: =AVERAGE(Table4[[#This Row],[2022]:[2024]]) -> 1.2234867e+08 | G23: Maintenance Inflation | H23: =AVERAGE((Table4[[#This Row],[2023]]/Table4[[#This Row],[2022]])-1,(Table4[[#This Row],[2024]]/Table4[[#This Row],[2023]])-1) -> 0.031987954
B24: Sales and Marketing | C24: =(100678)*1000 -> 100678000 | D24: =(114616)*1000 -> 114616000 | E24: =(106340)*1000 -> 106340000 | F24: =AVERAGE(Table4[[#This Row],[2022]:[2024]]) -> 1.0721133e+08
B25: Aircraft Lease Rentals | C25: =(23621)*1000 -> 23621000 | D25: =(24948)*1000 -> 24948000 | E25: =(23573)*1000 -> 23573000 | F25: =AVERAGE(Table4[[#This Row],[2022]:[2024]]) -> 24047333
B26: Other | C26: =(113532)*1000 -> 113532000 | D26: =(133501)*1000 -> 133501000 | E26: =(150399)*1000 -> 150399000 | F26: =AVERAGE(Table4[[#This Row],[2022]:[2024]]) -> 1.3247733e+08 | G26: Growth Rate | H26: =AVERAGE((Table4[[#This Row],[2023]]/Table4[[#This Row],[2022]])-1,(Table4[[#This Row],[2024]]/Table4[[#This Row],[2023]])-1) -> 0.15123228
B27: Special charges, nets of recoveries | C27: =(34612)*1000 -> 34612000 | D27: =(28645)*1000 -> 28645000 | E27: =(368131)*1000 -> 368131000 | F27: =AVERAGE(Table4[[#This Row],[2022]:[2024]]) -> 143796000
B29: Number of Passengers | C29: =16796544 -> 16796544 | D29: =17342236 -> 17342236 | E29: =16982836 -> 16982836 | G29: Avg Passenger Growth | H29: =AVERAGE(($D29/$C29)-1,($E29/$D29)-1) -> 0.0058821894
B30: TPP Revenue Per Passenger | C30: =(C$13)/C$29 -> 6.0107008 | D30: =(D$13)/D$29 -> 6.4916081 | E30: =(E$13)/E$29 -> 8.3689202 | G30: Avg TPP Growth | H30: =AVERAGE(($D30/$C30)-1,($E30/$D30)-1) -> 0.18459957
B31: Resort Revenue Per Passenger | C31: =C$15/C$29 -> 0.12925278 | D31: =D$15/D$29 -> 0.24985244 | E31: =E$15/E$29 -> 4.2832658 | G31: Resort Revenue Manual Rate | H31: 0.65
B32: Gallons of Fuel Consumed | C32: =218606000 -> 218606000 | D32: =224996000 -> 224996000 | E32: =227345000 -> 227345000 | G32: Fuel Consumption | H32: =AVERAGE(($D32/$C32)-1,($E32/$D32)-1) -> 0.019835428
B33: Percentage Marketing | C33: =C$24/SUM(C$12:C$15) -> 0.043738262 | D33: =D$24/SUM(D$12:D$15) -> 0.045666529 | E33: =E$24/SUM(E$12:E$15) -> 0.042322879 | F33: =F$24/SUM(F$12:F$15) -> 0.043913485
B34: Lease Rate | C34: =C$25/($C$5*12) -> 49210.417 | D34: =D$25/($C$5*12) -> 51975 | E34: =E$25/($C$5*12) -> 49110.417 | F34: =F$25/($C$5*12) -> 50098.611
L36: =A1 -> 0

Sheet Income Statement
B1: Allegiant Base Case Income Statement Forecast
B2: 2022–2024 Actuals | 2025–2030 Forecast
C4: Actuals | F4: Forecast
B5: Year | C5: 2022 | D5: 2023 | E5: 2024 | F5: =E$5+1 -> 2025 | G5: =F$5+1 -> 2026 | H5: =G$5+1 -> 2027 | I5: =H$5+1 -> 2028 | J5: =I$5+1 -> 2029 | K5: =J$5+1 -> 2030
B6: Operating Revenues
B7: {=Data!B12:B15} -> Passenger | C7: {=Data!C12:E15} -> 2137762000 | D7: 2324387000 | E7: 2217059000 | F7: =F$35*Data!$C$2 -> 3.7582011e+09 | G7: =G$35*Data!$C$2 -> 3.7803075e+09 | H7: =H$35*Data!$C$2 -> 3.802544e+09 | I7: =I$35*Data!$C$2 -> 3.8249113e+09 | J7: =J$35*Data!$C$2 -> 3.8474102e+09 | K7: =K$35*Data!$C$2 -> 3.8700414e+09
B8: Third Party Products | C8: 100959000 | D8: 112579000 | E8: 142128000 | F8: =F$35*F$36 -> 1.6935512e+08 | G8: =G$35*G$36 -> 2.0179808e+08 | H8: =H$35*H$36 -> 2.4045605e+08 | I8: =I$35*I$36 -> 2.8651964e+08 | J8: =J$35*J$36 -> 3.4140753e+08 | K8: =K$35*K$36 -> 4.0681015e+08
B9: Fixed Fee Contracts | C9: 60937000 | D9: 68548000 | E9: 80660000 | F9: =E$9*(1+Data!$H$14) -> 92823253 | G9: =F$9*(1+Data!$H$14) -> 1.0682068e+08 | H9: =G$9*(1+Data!$H$14) -> 1.2292888e+08 | I9: =H$9*(1+Data!$H$14) -> 1.4146614e+08 | J9: =I$9*(1+Data!$H$14) -> 1.6279875e+08 | K9: =J$9*(1+Data!$H$14) -> 1.8734824e+08
B10: Resort and Other | C10: 2171000 | D10: 4333000 | E10: 72742000 | F10: =F$35*F$37 -> 1.2073031e+08 | G10: =G$35*G$37 -> 2.0037677e+08 | H10: =H$35*H$37 -> 3.3256644e+08 | I10: =I$35*I$37 -> 5.5196239e+08 | J10: =J$35*J$37 -> 9.1609508e+08 | K10: =K$35*K$37 -> 1.5204481e+09
B11: Total Operating Revenues | C11: =SUM(C$7:C$10) -> 2301829000 | D11: =SUM(D$7:D$10) -> 2509847000 | E11: =SUM(E$7:E$10) -> 2512589000 | F11: =SUM(F$7:F$10) -> 4.1411098e+09 | G11: =SUM(G$7:G$10) -> 4.2893031e+09 | H11: =SUM(H$7:H$10) -> 4.4984954e+09 | I11: =SUM(I$7:I$10) -> 4.8048595e+09 | J11: =SUM(J$7:J$10) -> 5.2677115e+09 | K11: =SUM(K$7:K$10) -> 5.9846479e+09
B13: Operating Expenes
B14: Salaries and Benefits | C14: =Data!$C19 -> 552413000 | D14: =Data!$D19 -> 687803000 | E14: =Data!$E19 -> 819843000 | F14: =E$14*(1+Data!$H$19) -> 9.9900409e+08 | G14: =F$14*(1+Data!$H$19) -> 1.2173174e+09 | H14: =G$14*(1+Data!$H$19) -> 1.483339e+09 | I14: =H$14*(1+Data!$H$19) -> 1.8074945e+09 | J14: =I$14*(1+Data!$H$19) -> 2.202488e+09 | K14: =J$14*(1+Data!$H$19) -> 2.6837998e+09
B15: Aircraft Fuel | C15: =Data!$C20 -> 814803000 | D15: =Data!$D20 -> 695871000 | E15: =Data!$E20 -> 627755000 | F15: =F$38*Data!$C$4 -> 5.3326532e+08 | G15: =G$38*Data!$C$4 -> 5.4384286e+08 | H15: =H$38*Data!$C$4 -> 5.5463022e+08 | I15: =I$38*Data!$C$4 -> 5.6563155e+08 | J15: =J$38*Data!$C$4 -> 5.7685109e+08 | K15: =K$38*Data!$C$4 -> 5.8829318e+08
B16: Station Operations | C16: =Data!$C21 -> 255168000 | D16: =Data!$D21 -> 256560000 | E16: =Data!$E21 -> 272843000 | F16: =E$16*(1+Data!$H$21) -> 2.8224542e+08 | G16: =F$16*(1+Data!$H$21) -> 2.9197186e+08 | H16: =G$16*(1+Data!$H$21) -> 3.0203349e+08 | I16: =H$16*(1+Data!$H$21) -> 3.1244184e+08 | J16: =I$16*(1+Data!$H$21) -> 3.2320888e+08 | K16: =J$16*(1+Data!$H$21) -> 3.3434696e+08
B17: Depreciation and amoritzation | C17: =Data!$C22 -> 197542000 | D17: =Data!$D22 -> 223130000 | E17: =Data!$E22 -> 258251000 | F17: =E$17*(1+Data!$H$22) -> 2.9530143e+08 | G17: =F$17*(1+Data!$H$22) -> 3.3766736e+08 | H17: =G$17*(1+Data!$H$22) -> 3.8611139e+08 | I17: =H$17*(1+Data!$H$22) -> 4.4150553e+08 | J17: =I$17*(1+Data!$H$22) -> 5.0484688e+08 | K17: =J$17*(1+Data!$H$22) -> 5.7727562e+08
B18: Maintenance and Repairs | C18: =Data!$C23 -> 117814000 | D18: =Data!$D23 -> 123802000 | E18: =Data!$E23 -> 125430000 | F18: =E$18*(1+Data!$H$23) -> 1.2944225e+08 | G18: =F$18*(1+Data!$H$23) -> 1.3358284e+08 | H18: =G$18*(1+Data!$H$23) -> 1.3785588e+08 | I18: =H$18*(1+Data!$H$23) -> 1.4226561e+08 | J18: =I$18*(1+Data!$H$23) -> 1.468164e+08 | K18: =J$18*(1+Data!$H$23) -> 1.5151275e+08
B19: Sales and Marketing | C19: =Data!$C24 -> 100678000 | D19: =Data!$D24 -> 114616000 | E19: =Data!$E24 -> 106340000 | F19: =F$11*Data!$F$33 -> 1.8185056e+08 | G19: =G$11*Data!$F$33 -> 1.8835825e+08 | H19: =H$11*Data!$F$33 -> 1.9754461e+08 | I19: =I$11*Data!$F$33 -> 2.1099812e+08 | J19: =J$11*Data!$F$33 -> 2.3132357e+08 | K19: =K$11*Data!$F$33 -> 2.6280675e+08
B20: Aircraft Lease Rentals | C20: =Data!$C25 -> 23621000 | D20: =Data!$D25 -> 24948000 | E20: =Data!$E25 -> 23573000 | F20: =AVERAGE($C$20,$D$20,$E$20) -> 24047333 | G20: =AVERAGE($C$20,$D$20,$E$20) -> 24047333 | H20: =AVERAGE($C$20,$D$20,$E$20) -> 24047333 | I20: =AVERAGE($C$20,$D$20,$E$20) -> 24047333 | J20: =AVERAGE($C$20,$D$20,$E$20) -> 24047333 | K20: =AVERAGE($C$20,$D$20,$E$20) -> 24047333
B21: Other | C21: =Data!$C26 -> 113532000 | D21: =Data!$D26 -> 133501000 | E21: =Data!$E26 -> 150399000 | F21: =E$21*(1+Data!$H$26) -> 1.7314418e+08 | G21: =F$21*(1+Data!$H$26) -> 1.9932917e+08 | H21: =G$21*(1+Data!$H$26) -> 2.2947418e+08 | I21: =H$21*(1+Data!$H$26) -> 2.6417809e+08 | J21: =I$21*(1+Data!$H$26) -> 3.0413034e+08 | K21: =J$21*(1+Data!$H$26) -> 3.5012467e+08
B22: Special charges, nets of recoveries | C22: =Data!$C27 -> 34612000 | D22: =Data!$D27 -> 28645000 | E22: =Data!$E27 -> 368131000 | F22: =RANDBETWEEN($D$22,$E$22) -> 194732638 | G22: =RANDBETWEEN($D$22,$E$22) -> 132174797 | H22: =RANDBETWEEN($D$22,$E$22) -> 45062957 | I22: =RANDBETWEEN($D$22,$E$22) -> 198402678 | J22: =RANDBETWEEN($D$22,$E$22) -> 310609288 | K22: =RANDBETWEEN($D$22,$E$22) -> 263375970
B23: Total Operating Expenses | C23: =SUM(C$14:C$22) -> 2210183000 | D23: =SUM(D$14:D$22) -> 2288876000 | E23: =SUM(E$14:E$22) -> 2752565000 | F23: =SUM(F$14:F$22) -> 2.8130332e+09 | G23: =SUM(G$14:G$22) -> 3.0682919e+09 | H23: =SUM(H$14:H$22) -> 3.360099e+09 | I23: =SUM(I$14:I$22) -> 3.9669652e+09 | J23: =SUM(J$14:J$22) -> 4.6243218e+09 | K23: =SUM(K$14:K$22) -> 5.2355831e+09
B25: Operating Profit | C25: =C$11-C$23 -> 91646000 | D25: =D$11-D$23 -> 220971000 | E25: =E$11-E$23 -> -239976000 | F25: =F$11-F$23 -> 1.3280766e+09 | G25: =G$11-G$23 -> 1.2210112e+09 | H25: =H$11-H$23 -> 1.1383964e+09 | I25: =I$11-I$23 -> 8.3789426e+08 | J25: =J$11-J$23 -> 6.4338974e+08 | K25: =K$11-K$23 -> 7.4906484e+08
B34: Forecast Inputs
B35: Number of Passengers | C35: {=Data!C29:E29} -> 16796544 | D35: 17342236 | E35: 16982836 | F35: =E$35*(1+Data!$H$29) -> 17082732 | G35: =F$35*(1+Data!$H$29) -> 17183216 | H35: =G$35*(1+Data!$H$29) -> 17284291 | I35: =H$35*(1+Data!$H$29) -> 17385961 | J35: =I$35*(1+Data!$H$29) -> 17488228 | K35: =J$35*(1+Data!$H$29) -> 17591097
B36: {=Data!B30:E34} -> TPP Revenue Per Passenger | C36: 6.0107008 | D36: 6.4916081 | E36: 8.3689202 | F36: =E$36*(1+Data!$H$30) -> 9.9138193 | G36: =F$36*(1+Data!$H$30) -> 11.743906 | H36: =G$36*(1+Data!$H$30) -> 13.911826 | I36: =H$36*(1+Data!$H$30) -> 16.479943 | J36: =I$36*(1+Data!$H$30) -> 19.522134 | K36: =J$36*(1+Data!$H$30) -> 23.125911
B37: Resort Revenue Per Passenger | C37: 0.12925278 | D37: 0.24985244 | E37: 4.2832658 | F37: =E$37*(1+Data!$H$31) -> 7.0673885 | G37: =F$37*(1+Data!$H$31) -> 11.661191 | H37: =G$37*(1+Data!$H$31) -> 19.240965 | I37: =H$37*(1+Data!$H$31) -> 31.747593 | J37: =I$37*(1+Data!$H$31) -> 52.383528 | K37: =J$37*(1+Data!$H$31) -> 86.432821
B38: Gallons of Fuel Consumed | C38: 218606000 | D38: 224996000 | E38: 227345000 | F38: =E38*(1+Data!$H$32) -> 2.3185449e+08 | G38: =F38*(1+Data!$H$32) -> 2.3645342e+08 | H38: =G38*(1+Data!$H$32) -> 2.4114357e+08 | I38: =H38*(1+Data!$H$32) -> 2.4592676e+08 | J38: =I38*(1+Data!$H$32) -> 2.5080482e+08 | K38: =J38*(1+Data!$H$32) -> 2.5577964e+08
B39: Percentage Marketing | C39: 0.043738262 | D39: 0.045666529 | E39: 0.042322879
B40: Lease Rate | C40: 49210.417 | D40: 51975 | E40: 49110.417
B41: Note: Special Charges use RANDBETWEEN(), so values will recalculate each refresh.

Sheet Sheet1
B2: Most Profitable Year (Forecast) | C2: =_xlfn.XLOOKUP(D2,'Income Statement'!F25:K25,'Income Statement'!F5:K5) -> 2025 | D2: =MAX('Income Statement'!$F$25:$K$25) -> 1.3280766e+09
B3: Least Profitable Year (Forecast) | C3: =_xlfn.XLOOKUP(D3,'Income Statement'!F25:K25, 'Income Statement'!F5:K5) -> 2029 | D3: =MIN('Income Statement'!$F$25:$K$25) -> 6.4338974e+08
B4: Year of Highest Special Charges (Forecast) | C4: =_xlfn.XLOOKUP(D4,'Income Statement'!F22:K22,'Income Statement'!F5:K5) -> 2029 | D4: =MAX('Income Statement'!F22:K22) -> 310609288
B5: Year of Lowest Special Charges (Forecast) | C5: =_xlfn.XLOOKUP(D5,'Income Statement'!F22:K22,'Income Statement'!F5:K5) -> 2027 | D5: =MIN('Income Statement'!F22:K22) -> 45062957
